mcp_memgraph/__init__.py
mcp_memgraph/config.py
mcp_memgraph/main.py
mcp_memgraph/servers/__init__.py
mcp_memgraph/servers/memgraph_experimental.py
mcp_memgraph/servers/server.py
mcp_memgraph-0.1.9.dist-info/METADATA
mcp_memgraph-0.1.9.dist-info/WHEEL
mcp_memgraph-0.1.9.dist-info/entry_points.txt
mcp_memgraph-0.1.9.dist-info/licenses/LICENSE
mcp_memgraph-0.1.9.dist-info/RECORD
