Metadata-Version: 2.4
Name: mcp-memgraph
Version: 0.1.9
Summary: MCP integration and utilities for Memgraph MCP server
Project-URL: Homepage, https://github.com/memgraph/ai-toolkit
Project-URL: Source, https://github.com/memgraph/ai-toolkit/tree/main/integrations/mcp-memgraph
Project-URL: Issues, https://github.com/memgraph/ai-toolkit/issues
Author-email: antejavor <ante.javor@memgraph.io>
License: MIT
License-File: LICENSE
Keywords: graph,integration,mcp,memgraph,toolkit
Classifier: Intended Audience :: Developers
Classifier: License :: OSI Approved :: MIT License
Classifier: Programming Language :: Python :: 3
Classifier: Programming Language :: Python :: 3.13
Requires-Python: >=3.10
Requires-Dist: fastmcp>=2.13.0.2
Requires-Dist: httpx>=0.28.1
Requires-Dist: mcp[cli]>=1.9.3
Requires-Dist: memgraph-toolbox>=0.1.8
Requires-Dist: neo4j>=5.28.1
Requires-Dist: pytest>=8.3.5
Provides-Extra: test
Requires-Dist: anthropic; extra == 'test'
Requires-Dist: mcp[cli]>=1.3.0; extra == 'test'
Requires-Dist: pytest-asyncio>=0.20.3; extra == 'test'
Requires-Dist: pytest>=8.3.5; extra == 'test'
Requires-Dist: python-dotenv>=1.0.1; extra == 'test'
